ventus/__init__.py
ventus/cli.py
ventus/extension.py
ventus/filters.py
ventus/query.py
ventus/searcher.py
ventus/sites.py
ventus-0.3.4.dist-info/LICENSE
ventus-0.3.4.dist-info/METADATA
ventus-0.3.4.dist-info/WHEEL
ventus-0.3.4.dist-info/entry_points.txt
ventus-0.3.4.dist-info/top_level.txt
ventus-0.3.4.dist-info/RECORD
