Metadata-Version: 2.1
Name: ventus
Version: 0.3.4
Summary: A google dorking library and cli.
Home-page: https://github.com/aaronlyy/ventus
Author: aaronlyy (Aaron Levi)
Author-email: <aaronlevican@gmail.com>
Keywords: dorking,google,scraping,google dorking,hacking,cracking
Classifier: Intended Audience :: Developers
Classifier: Programming Language :: Python :: 3.6
Classifier: Programming Language :: Python :: 3.7
Classifier: Programming Language :: Python :: 3.8
Classifier: Programming Language :: Python :: 3.9
Classifier: Programming Language :: Python :: 3.10
Classifier: Programming Language :: Python :: 3.11
Classifier: Programming Language :: Python :: 3 :: Only
Classifier: Topic :: Software Development :: Libraries
Classifier: Operating System :: Unix
Classifier: Operating System :: MacOS :: MacOS X
Classifier: Operating System :: Microsoft :: Windows
License-File: LICENSE
Requires-Dist: requests
Requires-Dist: beautifulsoup4
Requires-Dist: click
